BlueWhale3_Timeseries-0.3.13-py3.8-nspkg.pth
orangecontrib/timeseries/__init__.py
orangecontrib/timeseries/agg_funcs.py
orangecontrib/timeseries/datasources.py
orangecontrib/timeseries/functions.py
orangecontrib/timeseries/i18n_config.py
orangecontrib/timeseries/models.py
orangecontrib/timeseries/timeseries.py
orangecontrib/timeseries/util.py
orangecontrib/timeseries/datasets/airpassengers.csv
orangecontrib/timeseries/locale/timeseries.en.yml
orangecontrib/timeseries/locale/timeseries.zh.yml
orangecontrib/timeseries/tests/__init__.py
orangecontrib/timeseries/tests/test_correlation.py
orangecontrib/timeseries/tests/test_doctests.py
orangecontrib/timeseries/tests/test_interpolation.py
orangecontrib/timeseries/tests/test_models.py
orangecontrib/timeseries/tests/test_periodogram.py
orangecontrib/timeseries/tests/test_seasonal.py
orangecontrib/timeseries/tests/test_timeseries.py
orangecontrib/timeseries/widgets/__init__.py
orangecontrib/timeseries/widgets/_owmodel.py
orangecontrib/timeseries/widgets/_rangeslider.py
orangecontrib/timeseries/widgets/_spiralogram.js
orangecontrib/timeseries/widgets/owaggregate.py
orangecontrib/timeseries/widgets/owarimamodel.py
orangecontrib/timeseries/widgets/owcorrelogram.py
orangecontrib/timeseries/widgets/owdifference.py
orangecontrib/timeseries/widgets/owgrangercausality.py
orangecontrib/timeseries/widgets/owinterpolate.py
orangecontrib/timeseries/widgets/owlinechart.py
orangecontrib/timeseries/widgets/owmodelevaluation.py
orangecontrib/timeseries/widgets/owmovingtransform.py
orangecontrib/timeseries/widgets/owperiodogram.py
orangecontrib/timeseries/widgets/owseasonaladjustment.py
orangecontrib/timeseries/widgets/owspiralogram.py
orangecontrib/timeseries/widgets/owtabletotimeseries.py
orangecontrib/timeseries/widgets/owtimeslice.py
orangecontrib/timeseries/widgets/owvarmodel.py
orangecontrib/timeseries/widgets/owyahoofinance.py
orangecontrib/timeseries/widgets/utils.py
orangecontrib/timeseries/widgets/highcharts/__init__.py
BlueWhale3_Timeseries-0.3.13.dist-info/LICENSE
BlueWhale3_Timeseries-0.3.13.dist-info/METADATA
BlueWhale3_Timeseries-0.3.13.dist-info/WHEEL
BlueWhale3_Timeseries-0.3.13.dist-info/entry_points.txt
BlueWhale3_Timeseries-0.3.13.dist-info/namespace_packages.txt
BlueWhale3_Timeseries-0.3.13.dist-info/top_level.txt
BlueWhale3_Timeseries-0.3.13.dist-info/RECORD
