Metadata-Version: 2.1
Name: BlueWhale3-Timeseries
Version: 0.3.13
Summary: 用于探索时间序列和顺序数据的蓝鲸插件。
Home-page: https://github.com/biolab/orange3-timeseries
Author: 大圣实验楼
Author-email: dashenglab@163.com
License: CC-BY-NC-3.0
Keywords: time series,sequence analysis,orange3 add-on,ARIMA,VAR model,forecast
Platform: UNKNOWN
Classifier: Development Status :: 4 - Beta
Classifier: Environment :: X11 Applications :: Qt
Classifier: Environment :: Plugins
Classifier: Programming Language :: Python
Classifier: License :: Other/Proprietary License
Classifier: Operating System :: OS Independent
Classifier: Topic :: Scientific/Engineering :: Artificial Intelligence
Classifier: Topic :: Scientific/Engineering :: Visualization
Classifier: Topic :: Software Development :: Libraries :: Python Modules
Classifier: Intended Audience :: Education
Classifier: Intended Audience :: Science/Research
Classifier: Intended Audience :: Developers
Requires-Dist: BlueWhale3
Requires-Dist: statsmodels (<0.13.0,>=0.10.0)
Requires-Dist: pandas
Requires-Dist: pandas-datareader
Requires-Dist: numpy
Requires-Dist: scipy (>=0.17)
Requires-Dist: more-itertools
Requires-Dist: python-dateutil
Provides-Extra: doc
Requires-Dist: sphinx ; extra == 'doc'
Requires-Dist: recommonmark ; extra == 'doc'
Requires-Dist: sphinx-rtd-theme ; extra == 'doc'
Provides-Extra: test
Requires-Dist: coverage ; extra == 'test'
